gitlab_ci_scripts/__init__.py
gitlab_ci_scripts/pycov_convert_relative_filenames.py
gitlab_ci_scripts-1.2.3.dist-info/LICENSE
gitlab_ci_scripts-1.2.3.dist-info/METADATA
gitlab_ci_scripts-1.2.3.dist-info/WHEEL
gitlab_ci_scripts-1.2.3.dist-info/entry_points.txt
gitlab_ci_scripts-1.2.3.dist-info/top_level.txt
gitlab_ci_scripts-1.2.3.dist-info/zip-safe
gitlab_ci_scripts-1.2.3.dist-info/RECORD
